ecr_lifecycle/__init__.py
ecr_lifecycle/__main__.py
ecr_lifecycle/args.py
ecr_lifecycle/ecr.py
ecr_lifecycle/logger.py
ecr_lifecycle-0.1.1.dist-info/LICENSE
ecr_lifecycle-0.1.1.dist-info/METADATA
ecr_lifecycle-0.1.1.dist-info/WHEEL
ecr_lifecycle-0.1.1.dist-info/entry_points.txt
ecr_lifecycle-0.1.1.dist-info/top_level.txt
ecr_lifecycle-0.1.1.dist-info/RECORD
