Metadata-Version: 2.1
Name: ecr-lifecycle
Version: 0.1.1
Summary: Delete old images tag inside ECR repository
Home-page: https://github.com/nanih98/python3-boto3-delete-ecr-images
Author: nanih98
Author-email: test@null.io
License: Apache
Classifier: Development Status :: 3 - Alpha
Classifier: Intended Audience :: End Users/Desktop
Classifier: License :: OSI Approved :: Apache Software License
Classifier: Operating System :: POSIX :: Linux
Classifier: Operating System :: MacOS
Classifier: Programming Language :: Python
Classifier: Programming Language :: Python :: 3.6
Classifier: Programming Language :: Python :: 3.7
Classifier: Programming Language :: Python :: 3.8
Classifier: Programming Language :: Python :: 3.9
Classifier: Programming Language :: Python :: 3.10
Requires-Python: >=3.6, <4
License-File: LICENSE
Requires-Dist: boto3 (==1.23.1)
Requires-Dist: botocore (==1.26.1)
Requires-Dist: jmespath (==1.0.0)
Requires-Dist: python-dateutil (==2.8.2)
Requires-Dist: s3transfer (==0.5.2)
Requires-Dist: six (==1.16.0)
Requires-Dist: urllib3 (==1.26.9)
